{"ua":"Mozilla\/5.0 (X11; Linux x86_64) AppleWebKit\/537.36 (KHTML, like Gecko) Chrome\/112.0.0.0 Safari\/537.36","old":"https:\/\/cdnjs.cloudflare.com\/ajax\/libs\/typescript\/4.0.7\/typescript.min.js","new":"https:\/\/cdnjs.cloudflare.com\/ajax\/libs\/typescript\/5.0.4\/typescript.min.js","comp":{"original":2847455,"br":{"1":937080,"2":848748,"3":838892,"4":798965,"5":736950,"6":722483,"7":711076,"8":705047,"9":700798,"10":647933,"11":638815},"sbr":{"1":937080,"2":848748,"3":838892,"4":798965,"5":604817,"6":598581,"7":592976,"8":589847,"9":587504,"10":530450,"11":520085}},"done":true}