{"ua":"Mozilla\/5.0 (Windows NT 10.0; Win64; x64) AppleWebKit\/537.36 (KHTML, like Gecko) Chrome\/111.0.0.0 Safari\/537.36 Edg\/111.0.1661.41","old":"https:\/\/web.archive.org\/web\/20230314000305js_\/https:\/\/www.youtube.com\/s\/player\/21246a91\/player_ias.vflset\/en_US\/base.js","new":"https:\/\/web.archive.org\/web\/20230317000137js_\/https:\/\/www.youtube.com\/s\/player\/59acb1f3\/player_ias.vflset\/en_US\/base.js","comp":{"original":2250556,"br":{"1":815142,"2":736625,"3":727892,"4":705772,"5":641203,"6":630889,"7":622874,"8":619607,"9":616349,"10":570166,"11":562087},"sbr":{"1":815142,"2":736656,"3":727892,"4":705772,"5":135522,"6":135754,"7":135956,"8":136301,"9":136366,"10":118661,"11":114059}},"done":true}